s3chunkuploader/__init__.py
s3chunkuploader/fields.py
s3chunkuploader/file_handler.py
s3chunkuploader/version.py
tests/__init__.py
tests/test_prefixed_keys.py
tests/fixtures/__init__.py
tests/fixtures/settings.py
s3chunkuploader-0.15.dist-info/LICENSE
s3chunkuploader-0.15.dist-info/METADATA
s3chunkuploader-0.15.dist-info/WHEEL
s3chunkuploader-0.15.dist-info/top_level.txt
s3chunkuploader-0.15.dist-info/RECORD
