Metadata-Version: 2.1
Name: s3chunkuploader
Version: 0.15
Summary: A Django/Django-Storages threaded S3 chunk uploader
Home-page: https://github.com/uktrade/s3chunkuploader
Author: Harel Malka
Author-email: harel@harelmalka.com
License: MIT
Platform: UNKNOWN
Classifier: Environment :: Web Environment
Classifier: Framework :: Django
Classifier: Framework :: Django :: 2.0
Classifier: Intended Audience :: Developers
Classifier: Operating System :: OS Independent
Classifier: Programming Language :: Python
Classifier: Programming Language :: Python :: 3.6
Classifier: Programming Language :: Python :: 3.7
Requires-Dist: boto3 (>=1.11.14)
Requires-Dist: Django (<3.2,>=2.0)
Requires-Dist: django-storages (<=1.9.1,>=1.7.2)
